{
	"configurations" : 
	[
		{
			"directories" : 
			[
				{
					"build" : ".",
					"childIndexes" : 
					[
						1
					],
					"hasInstallRule" : true,
					"jsonFile" : "directory-.-Debug-f5ebdc15457944623624.json",
					"minimumCMakeVersion" : 
					{
						"string" : "3.6.0"
					},
					"projectIndex" : 0,
					"source" : ".",
					"targetIndexes" : 
					[
						3,
						4
					]
				},
				{
					"build" : "third-party/openal",
					"hasInstallRule" : true,
					"jsonFile" : "directory-third-party.openal-Debug-0dcc8bbc2f4150a99f87.json",
					"minimumCMakeVersion" : 
					{
						"string" : "3.13"
					},
					"parentIndex" : 0,
					"projectIndex" : 1,
					"source" : "third-party/openal",
					"targetIndexes" : 
					[
						0,
						1,
						2
					]
				}
			],
			"name" : "Debug",
			"projects" : 
			[
				{
					"childIndexes" : 
					[
						1
					],
					"directoryIndexes" : 
					[
						0
					],
					"name" : "native-lib",
					"targetIndexes" : 
					[
						3,
						4
					]
				},
				{
					"directoryIndexes" : 
					[
						1
					],
					"name" : "OpenAL",
					"parentIndex" : 0,
					"targetIndexes" : 
					[
						0,
						1,
						2
					]
				}
			],
			"targets" : 
			[
				{
					"directoryIndex" : 1,
					"id" : "OpenAL::@c7389a3ac91fc6f83038",
					"jsonFile" : "target-OpenAL-Debug-9461965ade60bf805602.json",
					"name" : "OpenAL",
					"projectIndex" : 1
				},
				{
					"directoryIndex" : 1,
					"id" : "alsoft.common::@c7389a3ac91fc6f83038",
					"jsonFile" : "target-alsoft.common-Debug-a1b82bdc03cd03a3c4e8.json",
					"name" : "alsoft.common",
					"projectIndex" : 1
				},
				{
					"directoryIndex" : 1,
					"id" : "alsoft.excommon::@c7389a3ac91fc6f83038",
					"jsonFile" : "target-alsoft.excommon-Debug-970d70d2c11aac4e41e4.json",
					"name" : "alsoft.excommon",
					"projectIndex" : 1
				},
				{
					"directoryIndex" : 0,
					"id" : "app-glue::@6890427a1f51a3e7e1df",
					"jsonFile" : "target-app-glue-Debug-e56773b0e8f399d22247.json",
					"name" : "app-glue",
					"projectIndex" : 0
				},
				{
					"directoryIndex" : 0,
					"id" : "native-lib::@6890427a1f51a3e7e1df",
					"jsonFile" : "target-native-lib-Debug-6d64e7e9985c565aee91.json",
					"name" : "native-lib",
					"projectIndex" : 0
				}
			]
		}
	],
	"kind" : "codemodel",
	"paths" : 
	{
		"build" : "/home/bullydd/Documents/Android/vertex-academy/Masteringndk/02_ndk/app/.cxx/Debug/o5p395h2/arm64-v8a",
		"source" : "/home/bullydd/Documents/Android/vertex-academy/Masteringndk/02_ndk/app/src/main/cpp"
	},
	"version" : 
	{
		"major" : 2,
		"minor" : 3
	}
}
